TargetAPI/__init__.py
TargetAPI/_info.py
TargetAPI/helpers.py
TargetAPI/products.py
TargetAPI/stores.py
TargetAPI/target.py
TargetAPI-0.2.0.dist-info/METADATA
TargetAPI-0.2.0.dist-info/WHEEL
TargetAPI-0.2.0.dist-info/top_level.txt
TargetAPI-0.2.0.dist-info/RECORD
